stream_read_ods.py
stream_read_ods-0.0.22.dist-info/METADATA
stream_read_ods-0.0.22.dist-info/WHEEL
stream_read_ods-0.0.22.dist-info/licenses/LICENSE
stream_read_ods-0.0.22.dist-info/RECORD
