Metadata-Version: 2.1
Name: stream-read-ods
Version: 0.0.22
Summary: Python function to extract data from an ODS spreadsheet on the fly - without having to store the entire file in memory or disk
Project-URL: Source, https://github.com/uktrade/stream-read-ods
Author-email: Department for International Trade <sre@digital.trade.gov.uk>
License-File: LICENSE
Classifier: License :: OSI Approved :: MIT License
Classifier: Programming Language :: Python :: 3
Classifier: Topic :: System :: Archiving :: Compression
Requires-Python: >=3.7.1
Requires-Dist: lxml>=4.9.1
Requires-Dist: stream-unzip>=0.0.70
Provides-Extra: dev
Requires-Dist: coverage; extra == 'dev'
Requires-Dist: pytest; extra == 'dev'
Requires-Dist: pytest-cov; extra == 'dev'
Requires-Dist: stream-write-ods; extra == 'dev'
Requires-Dist: stream-zip; extra == 'dev'
